omniprompt/__init__.py
omniprompt/cli.py
omniprompt/providers.py
omniprompt/utils.py
omniprompt-1.0.0.dist-info/licenses/LICENSE
omniprompt-1.0.0.dist-info/METADATA
omniprompt-1.0.0.dist-info/WHEEL
omniprompt-1.0.0.dist-info/entry_points.txt
omniprompt-1.0.0.dist-info/top_level.txt
omniprompt-1.0.0.dist-info/RECORD
