Metadata-Version: 2.4
Name: omniprompt
Version: 1.0.0
Summary: A command-line utility for quickly testing and interacting with various LLM APIs.
Author: Andrew Kamau
License-Expression: MIT
Project-URL: Homepage, https://github.com/andkamau/omniprompt
Project-URL: Bug Tracker, https://github.com/andkamau/omniprompt/issues
Classifier: Programming Language :: Python :: 3
Classifier: Operating System :: OS Independent
Requires-Python: >=3.9
License-File: LICENSE
Requires-Dist: PyYAML
Requires-Dist: google-genai
Requires-Dist: openai
Requires-Dist: anthropic
Requires-Dist: groq
Requires-Dist: dashscope
Requires-Dist: rich
Requires-Dist: requests
Dynamic: license-file
